regressor/__init__.py
regressor/regress.cp38-win_amd64.pyd
regressor-1.0.9.dist-info/LICENSE.txt
regressor-1.0.9.dist-info/METADATA
regressor-1.0.9.dist-info/WHEEL
regressor-1.0.9.dist-info/top_level.txt
regressor-1.0.9.dist-info/RECORD
