Metadata-Version: 2.1
Name: regressor
Version: 1.0.9
Summary: Package for fast regression
Home-page: https://github.com/jeremymcrae/regressor
Author: Jeremy McRae
Author-email: jmcrae@illumina.com
License: MIT
Classifier: Development Status :: 4 - Beta
Classifier: Topic :: Scientific/Engineering :: Bio-Informatics
License-File: LICENSE.txt
Requires-Dist: numpy
Requires-Dist: scipy
